distjob/__init__.py
distjob/distjob_api.py
distjob/distjob_context.py
distjob/distjob_core.py
distjob/distjob_worker.py
distjob/test.py
distjob-0.1.0.dist-info/LICENSE
distjob-0.1.0.dist-info/METADATA
distjob-0.1.0.dist-info/WHEEL
distjob-0.1.0.dist-info/top_level.txt
distjob-0.1.0.dist-info/RECORD
